variantfoldrna/__about__.py
variantfoldrna/__init__.py
variantfoldrna/__main__.py
variantfoldrna/snk.yaml
variantfoldrna/cli/__init__.py
variantfoldrna/workflow/Snakefile
variantfoldrna/workflow/.snakemake/log/2024-09-27T111214.623646.snakemake.log
variantfoldrna/workflow/bin/chunk_extracted_seqs
variantfoldrna/workflow/bin/get_spliced_read_data
variantfoldrna/workflow/bin/riprap
variantfoldrna/workflow/bin/riprap1
variantfoldrna/workflow/bin/snpfold
variantfoldrna/workflow/bin/snpfold_wrapper
variantfoldrna/workflow/envs/agat.yaml
variantfoldrna/workflow/envs/ensembl.yaml
variantfoldrna/workflow/envs/general.yaml
variantfoldrna/workflow/envs/process_seq.yaml
variantfoldrna/workflow/envs/remurna.yaml
variantfoldrna/workflow/envs/riprap.yaml
variantfoldrna/workflow/envs/rnasnp.yaml
variantfoldrna/workflow/envs/snpeff_env.yaml
variantfoldrna/workflow/envs/snpfold.yaml
variantfoldrna/workflow/rules/chunk.smk
variantfoldrna/workflow/rules/combine_predictions.smk
variantfoldrna/workflow/rules/combine_predictions_csv.smk
variantfoldrna/workflow/rules/csv_rules_remurna.smk
variantfoldrna/workflow/rules/csv_rules_riprap.smk
variantfoldrna/workflow/rules/csv_rules_rnasnp.smk
variantfoldrna/workflow/rules/csv_rules_snpfold.smk
variantfoldrna/workflow/rules/extract_seqs.smk
variantfoldrna/workflow/rules/extract_seqs_spliced.smk
variantfoldrna/workflow/rules/remurna.smk
variantfoldrna/workflow/rules/riprap.smk
variantfoldrna/workflow/rules/rnasnp.smk
variantfoldrna/workflow/rules/snpfold.smk
variantfoldrna/workflow/rules/vcf_header.smk
variantfoldrna/workflow/rules/vep.smk
variantfoldrna/workflow/scripts/chunk_csv.py
variantfoldrna/workflow/scripts/chunk_extracted_seqs.py
variantfoldrna/workflow/scripts/chunk_vcf.py
variantfoldrna/workflow/scripts/combine_results.py
variantfoldrna/workflow/scripts/create_json_from_gffread_table.py
variantfoldrna/workflow/scripts/from_csv_remurna.py
variantfoldrna/workflow/scripts/from_csv_riprap.py
variantfoldrna-1.2.3.dist-info/METADATA
variantfoldrna-1.2.3.dist-info/WHEEL
variantfoldrna-1.2.3.dist-info/entry_points.txt
variantfoldrna-1.2.3.dist-info/licenses/LICENSE
variantfoldrna-1.2.3.dist-info/RECORD
