Metadata-Version: 2.3
Name: variantfoldrna
Version: 1.2.3
Project-URL: Documentation, https://github.com/The-Bevilacqua-Lab/variantfoldrna/wiki
Project-URL: Issues, https://github.com/The-Bevilacqua-Lab/variantfoldrna/issuess
Project-URL: Source, https://github.com/The-Bevilacqua-Lab/variantfoldrna
Author-email: Kobie-Kirven <kjkirven@presby.edu>
License-Expression: MIT
License-File: LICENSE
Classifier: Development Status :: 4 - Beta
Classifier: License :: OSI Approved :: MIT License
Classifier: Programming Language :: Python
Classifier: Programming Language :: Python :: 3.7
Classifier: Programming Language :: Python :: 3.8
Classifier: Programming Language :: Python :: 3.9
Classifier: Programming Language :: Python :: 3.10
Classifier: Programming Language :: Python :: 3.11
Classifier: Programming Language :: Python :: 3.12
Classifier: Programming Language :: Python :: Implementation :: CPython
Classifier: Programming Language :: Python :: Implementation :: PyPy
Requires-Python: >=3.7
Requires-Dist: snakemake==7.24.2
Requires-Dist: snk==0.22.2
